scrapme/__init__.py
scrapme/driver_manager.py
scrapme/exceptions.py
scrapme/rate_limiter.py
scrapme/selenium_scraper.py
scrapme/utils.py
scrapme/web_scraper.py
scrapme-1.8.8.dist-info/LICENSE
scrapme-1.8.8.dist-info/METADATA
scrapme-1.8.8.dist-info/WHEEL
scrapme-1.8.8.dist-info/top_level.txt
scrapme-1.8.8.dist-info/RECORD
