Metadata-Version: 2.1
Name: scrapme
Version: 1.8.8
Summary: A comprehensive web scraping framework featuring both static and dynamic content extraction, automatic Selenium/geckodriver management, rate limiting, proxy rotation, and Unicode support (including Georgian). Built with BeautifulSoup4 and Selenium, it provides an intuitive API for extracting text, tables, links and more from any web source.
Home-page: https://ubix.pro/
Author: N.Sikharulidze
Author-email: "N.Sikharulidze" <info@ubix.pro>
License: MIT License
Project-URL: Homepage, https://ubix.pro/
Project-URL: Documentation, https://github.com/NSb0y/scrapme
Project-URL: Repository, https://github.com/NSb0y/scrapme
Project-URL: Bug Tracker, https://github.com/NSb0y/scrapme/issues
Classifier: Programming Language :: Python :: 3
Classifier: License :: OSI Approved :: MIT License
Classifier: Operating System :: OS Independent
Classifier: Development Status :: 4 - Beta
Classifier: Intended Audience :: Developers
Classifier: Topic :: Internet :: WWW/HTTP
Classifier: Topic :: Software Development :: Libraries :: Python Modules
Requires-Python: >=3.8
License-File: LICENSE
Requires-Dist: beautifulsoup4>=4.9.0
Requires-Dist: requests>=2.25.0
Requires-Dist: pandas>=1.2.0
Requires-Dist: selenium>=4.0.0
Requires-Dist: trafilatura>=1.4.0
Requires-Dist: build>=1.2.2.post1
Requires-Dist: wheel>=0.44.0
Requires-Dist: setuptools>=75.2.0
